qsiprep/__init__.py
qsiprep/_version.py
qsiprep/_warnings.py
qsiprep/config.py
qsiprep/cli/__init__.py
qsiprep/cli/parser.py
qsiprep/cli/run.py
qsiprep/cli/version.py
qsiprep/cli/workflow.py
qsiprep/data/FreeSurfer2dseg.txt
qsiprep/data/FreeSurferColorLUT.txt
qsiprep/data/NOTICE
qsiprep/data/__init__.py
qsiprep/data/affine.json
qsiprep/data/b02b0_1.cnf
qsiprep/data/boilerplate.bib
qsiprep/data/eddy_params.json
qsiprep/data/eddy_params_testing.json
qsiprep/data/epi_atlasbased_brainmask.json
qsiprep/data/epi_registration_settings.json
qsiprep/data/fmap-any_registration.json
qsiprep/data/fmap-any_registration_testing.json
qsiprep/data/freesurfer_to_qsiprep.json
qsiprep/data/identitytransform.txt
qsiprep/data/intermodal_ACPC.json
qsiprep/data/intermodal_ACPC_sloppy.json
qsiprep/data/intramodal_ACPC.json
qsiprep/data/intramodal_ACPC_sloppy.json
qsiprep/data/intramodal_nonlinear.json
qsiprep/data/io_spec.json
qsiprep/data/itkIdentityTransform.txt
qsiprep/data/mni_lps_fmap_atlas.nii.gz
qsiprep/data/odfs.mat
qsiprep/data/quick_syn.json
qsiprep/data/reports-spec.yml
qsiprep/data/shoreline_coarse_Affine.json
qsiprep/data/shoreline_coarse_Rigid.json
qsiprep/data/shoreline_precise_Affine.json
qsiprep/data/shoreline_precise_Rigid.json
qsiprep/data/shoreline_sloppy_Affine.json
qsiprep/data/shoreline_sloppy_Rigid.json
qsiprep/data/susceptibility_syn.json
qsiprep/data/translation_rigid.json
qsiprep/data/schemes/ABCD.bval
qsiprep/data/schemes/ABCD.bvec
qsiprep/data/schemes/HCP.bval
qsiprep/data/schemes/HCP.bvec
qsiprep/data/tests/config.toml
qsiprep/interfaces/__init__.py
qsiprep/interfaces/anatomical.py
qsiprep/interfaces/ants.py
qsiprep/interfaces/bids.py
qsiprep/interfaces/confounds.py
qsiprep/interfaces/denoise.py
qsiprep/interfaces/dipy.py
qsiprep/interfaces/dsi_studio.py
qsiprep/interfaces/dwi_merge.py
qsiprep/interfaces/eddy.py
qsiprep/interfaces/epi_fmap.py
qsiprep/interfaces/fmap.py
qsiprep/interfaces/freesurfer.py
qsiprep/interfaces/gradients.py
qsiprep-1.1.1.dist-info/METADATA
qsiprep-1.1.1.dist-info/WHEEL
qsiprep-1.1.1.dist-info/entry_points.txt
qsiprep-1.1.1.dist-info/licenses/LICENSE
qsiprep-1.1.1.dist-info/RECORD
