Metadata-Version: 2.4
Name: QSIPrep
Version: 1.1.1
Summary: qsiprep builds workflows for preprocessing and reconstructing q-space images
Project-URL: Homepage, https://github.com/pennlinc/qsiprep
Project-URL: Documentation, https://www.qsiprep.readthedocs.io
Project-URL: Paper, https://doi.org/10.1038/s41592-022-01458-7
Project-URL: Docker Images, https://hub.docker.com/r/pennlinc/qsiprep/tags/
Author: The PennLINC developers
License: Copyright (c) 2015-2018, the BBL developers team.
License-File: LICENSE
Classifier: Development Status :: 3 - Alpha
Classifier: Intended Audience :: Science/Research
Classifier: License :: OSI Approved :: BSD License
Classifier: Programming Language :: Python :: 3.10
Classifier: Topic :: Scientific/Engineering :: Image Recognition
Requires-Python: >=3.10
Requires-Dist: acres
Requires-Dist: dipy<1.12.0,>=1.11.0
Requires-Dist: fury
Requires-Dist: importlib-resources; python_version < '3.11'
Requires-Dist: indexed-gzip<=1.8.7
Requires-Dist: jinja2<3.1
Requires-Dist: matplotlib
Requires-Dist: networkx~=2.8.8
Requires-Dist: nibabel<=5.2.0
Requires-Dist: nilearn==0.10.1
Requires-Dist: nipype==1.9.1
Requires-Dist: nireports>=24.0.3
Requires-Dist: niworkflows<=1.10,>=1.9
Requires-Dist: numpy<=1.26.3
Requires-Dist: pandas<2.0.0
Requires-Dist: psutil<=5.9.8
Requires-Dist: pybids
Requires-Dist: pyyaml
Requires-Dist: scikit-image
Requires-Dist: scikit-learn<=1.4.0
Requires-Dist: seaborn
Requires-Dist: sentry-sdk
Requires-Dist: simpleitk
Requires-Dist: surfa==0.6.1
Requires-Dist: svgutils<=0.3.4
Requires-Dist: transforms3d
Requires-Dist: vtk
Requires-Dist: xvfbwrapper
Provides-Extra: all
Requires-Dist: coverage; extra == 'all'
Requires-Dist: dipy; extra == 'all'
Requires-Dist: doctest-ignore-unicode; extra == 'all'
Requires-Dist: fuzzywuzzy; extra == 'all'
Requires-Dist: lxml-html-clean; extra == 'all'
Requires-Dist: nbsphinx; extra == 'all'
Requires-Dist: pre-commit; extra == 'all'
Requires-Dist: pydot>=1.2.3; extra == 'all'
Requires-Dist: pydotplus; extra == 'all'
Requires-Dist: pytest; extra == 'all'
Requires-Dist: pytest-cov; extra == 'all'
Requires-Dist: pytest-env; extra == 'all'
Requires-Dist: pytest-xdist; extra == 'all'
Requires-Dist: python-levenshtein; extra == 'all'
Requires-Dist: recommonmark; extra == 'all'
Requires-Dist: ruff~=0.4.3; extra == 'all'
Requires-Dist: sphinx-argparse; extra == 'all'
Requires-Dist: sphinx-markdown-tables; extra == 'all'
Requires-Dist: sphinx-rtd-theme; extra == 'all'
Requires-Dist: sphinx>=4.2.0; extra == 'all'
Requires-Dist: sphinxcontrib-apidoc; extra == 'all'
Requires-Dist: sphinxcontrib-bibtex; extra == 'all'
Provides-Extra: dev
Requires-Dist: pre-commit; extra == 'dev'
Requires-Dist: ruff~=0.4.3; extra == 'dev'
Provides-Extra: doc
Requires-Dist: dipy; extra == 'doc'
Requires-Dist: doctest-ignore-unicode; extra == 'doc'
Requires-Dist: lxml-html-clean; extra == 'doc'
Requires-Dist: nbsphinx; extra == 'doc'
Requires-Dist: pydot>=1.2.3; extra == 'doc'
Requires-Dist: pydotplus; extra == 'doc'
Requires-Dist: recommonmark; extra == 'doc'
Requires-Dist: sphinx-argparse; extra == 'doc'
Requires-Dist: sphinx-markdown-tables; extra == 'doc'
Requires-Dist: sphinx-rtd-theme; extra == 'doc'
Requires-Dist: sphinx>=4.2.0; extra == 'doc'
Requires-Dist: sphinxcontrib-apidoc; extra == 'doc'
Requires-Dist: sphinxcontrib-bibtex; extra == 'doc'
Provides-Extra: maint
Requires-Dist: fuzzywuzzy; extra == 'maint'
Requires-Dist: python-levenshtein; extra == 'maint'
Provides-Extra: tests
Requires-Dist: coverage; extra == 'tests'
Requires-Dist: pytest; extra == 'tests'
Requires-Dist: pytest-cov; extra == 'tests'
Requires-Dist: pytest-env; extra == 'tests'
Requires-Dist: pytest-xdist; extra == 'tests'
